hello_python_empty_package/__init__.py
hello_python_empty_package/daominahmath.py
hello_python_empty_package/daominahmath_test.py
hello_python_empty_package-0.1.3.dist-info/licenses/LICENSE
hello_python_empty_package-0.1.3.dist-info/METADATA
hello_python_empty_package-0.1.3.dist-info/WHEEL
hello_python_empty_package-0.1.3.dist-info/top_level.txt
hello_python_empty_package-0.1.3.dist-info/RECORD
