Metadata-Version: 2.4
Name: hello_python_empty_package
Version: 0.1.3
Summary: An empty Python project template with an add function.
Author-email: daominah <tung.daothanhtung@gmail.com>
License: BSD 2-Clause License
Project-URL: Source, https://github.com/daominah/hello_python_empty_package
Requires-Python: >=3.7
License-File: LICENSE
Dynamic: license-file
